.gitignore
LICENSE
MANIFEST.in
README.rst
contributors.txt
setup.cfg
setup.py
cluspro_api/__init__.py
cluspro_api/cmd_download.py
cluspro_api/cmd_submit.py
cluspro_api/config.py
cluspro_api/version.py
cluspro_api.egg-info/PKG-INFO
cluspro_api.egg-info/SOURCES.txt
cluspro_api.egg-info/dependency_links.txt
cluspro_api.egg-info/entry_points.txt
cluspro_api.egg-info/requires.txt
cluspro_api.egg-info/top_level.txt
cluspro_api/pymol/__init__.py
cluspro_api/pymol/importing.py
requirements/development.txt