Metadata-Version: 1.1
Name: cluspro-api
Version: 1.0.4
Summary: Library for submitting and downloading job data from ClusPro.
Home-page: https://bitbucket.org/bu-structure/cluspro_api
Author: Katie Porter
Author-email: kaporter@bu.edu
License: MIT
Keywords: cluspro protein
Platform: UNKNOWN
Classifier: Development Status :: 3 - Alpha
Classifier: Intended Audience :: Science/Research
Classifier: License :: OSI Approved :: MIT License
Classifier: Operating System :: MacOS
Classifier: Operating System :: POSIX
Classifier: Programming Language :: Python :: 3.4
Classifier: Programming Language :: Python :: 3.5
Classifier: Programming Language :: Python :: 3.6
Classifier: Topic :: Scientific/Engineering :: Bio-Informatics
